run_SnapFISH.py
src/SingleChrProcessor.py
src/SnapFISH.py
src/__init__.py
src/__main__.py
SnapFISH-0.1.0.dist-info/LICENSE
SnapFISH-0.1.0.dist-info/METADATA
SnapFISH-0.1.0.dist-info/WHEEL
SnapFISH-0.1.0.dist-info/entry_points.txt
SnapFISH-0.1.0.dist-info/top_level.txt
SnapFISH-0.1.0.dist-info/RECORD
